jwt_ninja/__init__.py
jwt_ninja/admin.py
jwt_ninja/api.py
jwt_ninja/auth_classes.py
jwt_ninja/authenticators.py
jwt_ninja/cryptography.py
jwt_ninja/errors.py
jwt_ninja/handlers.py
jwt_ninja/models.py
jwt_ninja/request.py
jwt_ninja/settings.py
jwt_ninja/types.py
jwt_ninja/migrations/0001_initial.py
jwt_ninja/migrations/__init__.py
jwt_ninja/tests/__init__.py
jwt_ninja/tests/conftest.py
jwt_ninja/tests/django_settings.py
jwt_ninja/tests/test_api_endpoints.py
jwt_ninja/tests/test_jwt_auth.py
jwtninja-0.1.25.dist-info/METADATA
jwtninja-0.1.25.dist-info/WHEEL
jwtninja-0.1.25.dist-info/licenses/LICENSE
jwtninja-0.1.25.dist-info/RECORD
