Metadata-Version: 2.4
Name: jwtninja
Version: 0.1.25
Summary: A simple and fully-typed auth library for Django Ninja based on PyJWT.
Project-URL: Homepage, https://github.com/dvf/jwt-ninja
License-File: LICENSE
Requires-Python: >=3.12
Requires-Dist: django-ninja>=1.3.0
Requires-Dist: pydantic-settings>=2.5.2
Requires-Dist: pydantic>=2.9.2
Requires-Dist: pyjwt>=2.9.0
Requires-Dist: uuid6>=2024.7.10
